telefolders/__init__.py
telefolders/__main__.py
telefolders/eel_functions.py
telefolders/tg.py
telefolders/web/css/components.css
telefolders/web/css/components.css.map
telefolders/web/css/components.scss
telefolders/web/css/fonts.css
telefolders/web/css/fonts.css.map
telefolders/web/css/fonts.scss
telefolders/web/css/reset.css
telefolders/web/css/reset.css.map
telefolders/web/css/reset.scss
telefolders/web/css/style.css
telefolders/web/css/style.css.map
telefolders/web/css/style.scss
telefolders/web/img/archived.png
telefolders/web/img/bots.png
telefolders/web/img/channels.png
telefolders/web/img/contacts.png
telefolders/web/img/custom.png
telefolders/web/img/groups.png
telefolders/web/img/muted.png
telefolders/web/img/noncontacts.png
telefolders/web/img/read.png
telefolders/web/img/svg/close.svg
telefolders/web/img/svg/left-row.svg
telefolders/web/img/svg/minus-black.svg
telefolders/web/img/svg/minus-white.svg
telefolders/web/img/svg/pin-black.svg
telefolders/web/img/svg/pin-white.svg
telefolders/web/img/svg/plus-black.svg
telefolders/web/img/svg/plus-white.svg
telefolders/web/img/svg/right-row.svg
telefolders/web/js/components/FloatViewWidget/index.js
telefolders/web/js/components/HeaderWidget/index.js
telefolders/web/js/components/LoginWidget/index.js
telefolders/web/js/components/MainWidget/index.js
telefolders/web/js/components/PopupWidget/index.js
telefolders/web/js/components/TableWidget/index.js
telefolders/web/js/main.js
telefolders/web/jsdoc.config.json
telefolders/web/main.html
telefolders-0.2.1.dist-info/LICENSE
telefolders-0.2.1.dist-info/METADATA
telefolders-0.2.1.dist-info/WHEEL
telefolders-0.2.1.dist-info/RECORD
