Metadata-Version: 2.1
Name: telefolders
Version: 0.2.1
Summary: TeleFolders is a folder and chatmanager designed for Telegram
Home-page: https://github.com/Noradrenalin-team/TeleFolders
License: MIT
Author: Dmitry (DevDK)
Author-email: Dmitry@kolyadin.me
Requires-Python: ==3.11.*
Classifier: License :: OSI Approved :: MIT License
Classifier: Programming Language :: Python :: 3
Classifier: Programming Language :: Python :: 3.11
Requires-Dist: eel (>=0.16.0,<0.17.0)
Requires-Dist: telethon (>=1.34.0,<2.0.0)
Project-URL: Repository, https://github.com/Noradrenalin-team/TeleFolders
